musicapy/__init__.py
musicapy/saavn_api/__init__.py
musicapy/saavn_api/__main__.py
musicapy/saavn_api/api.py
musicapy/saavn_api/config.py
musicapy/saavn_api/endpoint.py
musicapy/saavn_api/services.py
musicapy/saavn_api/utils.py
musicapy-2.2.1.dist-info/LICENSE
musicapy-2.2.1.dist-info/METADATA
musicapy-2.2.1.dist-info/WHEEL
musicapy-2.2.1.dist-info/RECORD
