Metadata-Version: 2.1
Name: musicapy
Version: 2.2.1
Summary: Python wrapper for several music platforms API
License: MIT
Author: Dhrumil Mistry
Author-email: 56185972+dmdhrumilmistry@users.noreply.github.com
Requires-Python: >=3.8,<4.0
Classifier: License :: OSI Approved :: MIT License
Classifier: Programming Language :: Python :: 3
Classifier: Programming Language :: Python :: 3.8
Classifier: Programming Language :: Python :: 3.9
Classifier: Programming Language :: Python :: 3.10
Classifier: Programming Language :: Python :: 3.11
Provides-Extra: docs
Requires-Dist: myst-parser (>=1.0.0,<2.0.0) ; extra == "docs"
Requires-Dist: requests (>=2.28.2,<3.0.0)
Requires-Dist: sphinx (>=6.1.3,<7.0.0) ; extra == "docs"
Requires-Dist: sphinx-rtd-theme (>=1.2.0,<2.0.0) ; extra == "docs"
Requires-Dist: wget (>=3.2,<4.0)
Project-URL: Bug Tracker, https://github.com/dmdhrumilmistry/MusicAPy/issues
Project-URL: Home, https://github.com/dmdhrumilmistry/MusicAPy
Project-URL: PayPal, https://paypal.me/dmdhrumilmistry
Project-URL: Support, https://github.com/sponsors/dmdhrumilmistry/
